cai_causalnet/__init__.py
cai_causalnet-0.0.0.dist-info/WHEEL
cai_causalnet-0.0.0.dist-info/METADATA
cai_causalnet-0.0.0.dist-info/RECORD
